setup.py
pwbmgraphing/__init__.py
pwbmgraphing/utilities.py
pwbmgraphing/visualizations.py
pwbmgraphing.egg-info/PKG-INFO
pwbmgraphing.egg-info/SOURCES.txt
pwbmgraphing.egg-info/dependency_links.txt
pwbmgraphing.egg-info/not-zip-safe
pwbmgraphing.egg-info/requires.txt
pwbmgraphing.egg-info/top_level.txt