Metadata-Version: 1.0
Name: pwbmgraphing
Version: 0.1
Summary: Graphing functions for PWBM
Home-page: https://github.com/PennWhartonBudgetModel/pwbmgraphing
Author: Penn Wharton Budget Model
Author-email: UNKNOWN
License: UNKNOWN
Platform: UNKNOWN
